vizro/__init__.py
vizro/_constants.py
vizro/_vizro.py
vizro/_vizro_utils.py
vizro/py.typed
vizro/_themes/__init__.py
vizro/_themes/_colors.py
vizro/_themes/_palettes.py
vizro/_themes/_static_template_generator.py
vizro/_themes/_templates.py
vizro/_themes/vizro_dark.json
vizro/_themes/vizro_light.json
vizro/actions/__init__.py
vizro/actions/_abstract_action.py
vizro/actions/_actions_utils.py
vizro/actions/_export_data.py
vizro/actions/_filter_action.py
vizro/actions/_filter_interaction.py
vizro/actions/_notifications.py
vizro/actions/_on_page_load.py
vizro/actions/_parameter_action.py
vizro/actions/_set_control.py
vizro/charts/__init__.py
vizro/charts/_charts_utils.py
vizro/figures/__init__.py
vizro/figures/library.py
vizro/integrations/__init__.py
vizro/integrations/kedro/__init__.py
vizro/integrations/kedro/_data_manager.py
vizro/managers/__init__.py
vizro/managers/_data_manager.py
vizro/managers/_managers_utils.py
vizro/managers/_model_manager.py
vizro/models/__init__.py
vizro/models/_base.py
vizro/models/_dashboard.py
vizro/models/_flex.py
vizro/models/_grid.py
vizro/models/_models_utils.py
vizro/models/_page.py
vizro/models/_tooltip.py
vizro/models/types.py
vizro/models/_action/__init__.py
vizro/models/_action/_action.py
vizro/models/_components/__init__.py
vizro/models/_components/_components_utils.py
vizro/models/_components/_form.py
vizro/models/_components/ag_grid.py
vizro/models/_components/button.py
vizro/models/_components/card.py
vizro/models/_components/container.py
vizro/models/_components/figure.py
vizro/models/_components/graph.py
vizro/models/_components/table.py
vizro/models/_components/tabs.py
vizro/models/_components/text.py
vizro/models/_components/form/__init__.py
vizro/models/_components/form/_form_utils.py
vizro/models/_components/form/_text_area.py
vizro/models/_components/form/_user_input.py
vizro/models/_components/form/checklist.py
vizro/models/_components/form/date_picker.py
vizro/models/_components/form/dropdown.py
vizro-0.1.51.dist-info/METADATA
vizro-0.1.51.dist-info/WHEEL
vizro-0.1.51.dist-info/licenses/LICENSE.txt
vizro-0.1.51.dist-info/RECORD
