Metadata-Version: 2.4
Name: vizro
Version: 0.1.51
Summary: Vizro is a low-code framework for building high-quality data visualization apps.
Project-URL: Documentation, https://github.com/mckinsey/vizro#readme
Project-URL: Issues, https://github.com/mckinsey/vizro/issues
Project-URL: Source, https://github.com/mckinsey/vizro
Author: Vizro Team
License-File: LICENSE.txt
Classifier: Programming Language :: Python
Classifier: Programming Language :: Python :: 3.10
Classifier: Programming Language :: Python :: 3.11
Classifier: Programming Language :: Python :: 3.12
Classifier: Programming Language :: Python :: 3.13
Classifier: Programming Language :: Python :: 3.14
Requires-Python: >=3.10
Requires-Dist: autoflake
Requires-Dist: black
Requires-Dist: dash-ag-grid>=31.3.1
Requires-Dist: dash-bootstrap-components>=2
Requires-Dist: dash-mantine-components>=2.0.0
Requires-Dist: dash<4,>=3.4.0
Requires-Dist: flask-caching>=2
Requires-Dist: packaging
Requires-Dist: pandas>=2
Requires-Dist: plotly>=5.24.0
Requires-Dist: pydantic>=2.7.0
Requires-Dist: python-box
Requires-Dist: wrapt>=1
Provides-Extra: kedro
Requires-Dist: kedro-datasets; extra == 'kedro'
Requires-Dist: kedro>=0.19.9; extra == 'kedro'
